README.md
setup.cfg
setup.py
sans_distributions/Binomialdistribution.py
sans_distributions/Gaussiandistribution.py
sans_distributions/Generaldistribution.py
sans_distributions/__init__.py
sans_distributions.egg-info/PKG-INFO
sans_distributions.egg-info/SOURCES.txt
sans_distributions.egg-info/dependency_links.txt
sans_distributions.egg-info/not-zip-safe
sans_distributions.egg-info/top_level.txt